grutopia/__init__.py
grutopia/download_assets.py
grutopia/login_openxlab.py
grutopia/macros.py
grutopia/set_assets_path.py
grutopia/setup_conda_pypi.py
grutopia/core/__init__.py
grutopia/core/gym_env.py
grutopia/core/runner.py
grutopia/core/config/__init__.py
grutopia/core/config/metric/__init__.py
grutopia/core/config/robot/__init__.py
grutopia/core/config/scene/__init__.py
grutopia/core/config/scene/object_params/__init__.py
grutopia/core/config/scene/object_params/dynamic_cube.py
grutopia/core/config/scene/object_params/usd_obj.py
grutopia/core/config/task/__init__.py
grutopia/core/config/task/episode.py
grutopia/core/config/task/reward.py
grutopia/core/datahub/__init__.py
grutopia/core/datahub/datahub.py
grutopia/core/datahub/isaac_data.py
grutopia/core/datahub/model_data.py
grutopia/core/register/__init__.py
grutopia/core/register/register.py
grutopia/core/robot/__init__.py
grutopia/core/robot/controller.py
grutopia/core/robot/robot.py
grutopia/core/robot/sensor.py
grutopia/core/runtime/__init__.py
grutopia/core/runtime/distributed_task_runtime_manager.py
grutopia/core/runtime/local_task_runtime_manager.py
grutopia/core/runtime/task_runtime.py
grutopia/core/scene/__init__.py
grutopia/core/scene/object.py
grutopia/core/scene/scene/__init__.py
grutopia/core/scene/scene/util/__init__.py
grutopia/core/scene/scene/util/usd_op.py
grutopia/core/scene/scene/util/type/__init__.py
grutopia/core/scene/scene/util/type/type_map.py
grutopia/core/task/__init__.py
grutopia/core/task/metric.py
grutopia/core/task/reward.py
grutopia/core/task/task.py
grutopia/core/util/__init__.py
grutopia/core/util/async_req.py
grutopia/core/util/clear_task.py
grutopia/core/util/gym.py
grutopia/core/util/interaction.py
grutopia/core/util/joint.py
grutopia/core/util/math.py
grutopia/core/util/omni_usd_util.py
grutopia/core/util/physics.py
grutopia/core/util/python.py
grutopia/core/util/space.py
grutopia/core/util/chat/__init__.py
grutopia/core/util/chat/agent_chat.py
grutopia-2.1.1.dist-info/licenses/LICENSE
grutopia-2.1.1.dist-info/METADATA
grutopia-2.1.1.dist-info/WHEEL
grutopia-2.1.1.dist-info/top_level.txt
grutopia-2.1.1.dist-info/RECORD
